spectral_denoising/__init__.py
spectral_denoising/chem_utils.py
spectral_denoising/constant.py
spectral_denoising/denoising_search.py
spectral_denoising/file_io.py
spectral_denoising/identifier_utils.py
spectral_denoising/noise.py
spectral_denoising/other_helpers.py
spectral_denoising/search_utils.py
spectral_denoising/seven_golden_rules.py
spectral_denoising/spectra_plotter.py
spectral_denoising/spectral_denoising.py
spectral_denoising/spectral_operations.py
spectral_denoising/test.py
src/__init__.py
src/chem_utils.py
src/constant.py
src/denoising_search.py
src/file_io.py
src/identifier_utils.py
src/noise.py
src/search_utils.py
src/seven_golden_rules.py
src/spectra_plotter.py
src/spectral_denoising.py
src/spectral_operations.py
spectral_denoising-0.4.2.dist-info/LICENSE
spectral_denoising-0.4.2.dist-info/METADATA
spectral_denoising-0.4.2.dist-info/WHEEL
spectral_denoising-0.4.2.dist-info/top_level.txt
spectral_denoising-0.4.2.dist-info/RECORD
